ocelot/__init__.py
ocelot/constants.py
ocelot/core.py
ocelot/pseudopotential.py
ocelot/visualizations.py
ocelot/wavefunction.py
ocelot_quantum-0.0.7.dist-info/LICENSE.txt
ocelot_quantum-0.0.7.dist-info/METADATA
ocelot_quantum-0.0.7.dist-info/WHEEL
ocelot_quantum-0.0.7.dist-info/top_level.txt
ocelot_quantum-0.0.7.dist-info/RECORD
